rsplan/__init__.py
rsplan/curves.py
rsplan/demo.py
rsplan/helpers.py
rsplan/planner.py
rsplan/primitives.py
rsplan/py.typed
rsplan/unit_tests.py
rsplan-1.0.10.dist-info/LICENSE
rsplan-1.0.10.dist-info/METADATA
rsplan-1.0.10.dist-info/WHEEL
rsplan-1.0.10.dist-info/top_level.txt
rsplan-1.0.10.dist-info/RECORD
