Metadata-Version: 2.1
Name: rsplan
Version: 1.0.10
Summary: Reeds-Shepp algorithm implementation in Python.
Home-page: https://github.com/builtrobotics/rsplan
Author: Built Robotics
Author-email: engineering@builtrobotics.com
License: MIT
Keywords: reeds-shepp path planning
Platform: UNKNOWN
Classifier: License :: OSI Approved :: MIT License
Classifier: Programming Language :: Python
Classifier: Programming Language :: Python :: 3
